example_package_skymap/__init__.py
example_package_skymap/data.py
example_package_skymap-0.0.5.dist-info/LICENSE
example_package_skymap-0.0.5.dist-info/METADATA
example_package_skymap-0.0.5.dist-info/WHEEL
example_package_skymap-0.0.5.dist-info/top_level.txt
example_package_skymap-0.0.5.dist-info/RECORD
