Metadata-Version: 2.1
Name: example-package-skymap
Version: 0.0.5
Summary: A small example package
Author: Nguyen Van Trien
Author-email: trien.nv195934@gmail.com
Keywords: python,eofactory,skymap,data
Classifier: Programming Language :: Python :: 3
Classifier: License :: OSI Approved :: MIT License
Classifier: Operating System :: OS Independent
Classifier: Operating System :: Microsoft :: Windows
License-File: LICENSE
Requires-Dist: python-dotenv
